provide_to_student/.env
provide_to_student/__init__.py
provide_to_student/new.py
provide_to_student/script.tcl
LLM4HW-0.9.dist-info/METADATA
LLM4HW-0.9.dist-info/WHEEL
LLM4HW-0.9.dist-info/top_level.txt
LLM4HW-0.9.dist-info/RECORD
