Metadata-Version: 2.1
Name: LLM4HW
Version: 0.9
Summary: Everything you need to install for the LLM4HW tool
Home-page: https://github.com/annnnie-qiu/annie_install.git
Author: Siyu Qiu
Author-email: siyu.qiu1@unsw.edu.au
Classifier: Programming Language :: Python :: 3
Classifier: License :: OSI Approved :: MIT License
Classifier: Operating System :: OS Independent
Requires-Python: >=3.6
Requires-Dist: numpy
Requires-Dist: openai
Requires-Dist: Flask
Requires-Dist: requests
Requires-Dist: python-dotenv
